<?xml version="1.0" encoding="utf-8"?>
<!DOCTYPE hibernate-mapping PUBLIC "-//Hibernate/Hibernate Mapping DTD 3.0//EN"
"http://hibernate.sourceforge.net/hibernate-mapping-3.0.dtd">
<!-- 
    Mapping file autogenerated by MyEclipse Persistence Tools
-->
<hibernate-mapping>
    <class name="com.converter.TabComponentInfo" table="TAB_COMPONENT_INFO" schema="PCBVI">
        <composite-id name="id" class="com.converter.TabComponentInfoId">
            <key-property name="itemNo" type="java.lang.String">
                <column name="ITEM_NO" length="20" />
            </key-property>
            <key-property name="as" type="java.lang.String">
                <column name="AS_" length="5" />
            </key-property>
            <key-property name="refdes" type="java.lang.String">
                <column name="REFDES" length="15" />
            </key-property>
        </composite-id>
        <property name="ppi" type="java.math.BigDecimal">
            <column name="PPI" precision="22" scale="0" />
        </property>
        <property name="componentNumber" type="java.lang.String">
            <column name="COMPONENT_NUMBER" length="20" />
        </property>
        <property name="componentAs" type="java.lang.String">
            <column name="COMPONENT_AS" length="5" />
        </property>
        <property name="componentPpi" type="java.math.BigDecimal">
            <column name="COMPONENT_PPI" precision="22" scale="0" />
        </property>
        <property name="fillColor" type="java.lang.String">
            <column name="FILL_COLOR" length="15" />
        </property>
        <property name="strokeWidth" type="java.lang.String">
            <column name="STROKE_WIDTH" length="10" />
        </property>
        <property name="strokeColor" type="java.lang.String">
            <column name="STROKE_COLOR" length="15" />
        </property>
        <property name="eventTime" type="java.sql.Timestamp">
            <column name="EVENT_TIME" length="7" />
        </property>
    </class>
</hibernate-mapping>
